Weight_Matrix/Weight_Matrix.py
Weight_Matrix/__init__.py
Weight_Matrix-0.0.1.dist-info/METADATA
Weight_Matrix-0.0.1.dist-info/WHEEL
Weight_Matrix-0.0.1.dist-info/top_level.txt
Weight_Matrix-0.0.1.dist-info/RECORD
